howdoi/__init__.py
howdoi/cli.py
howdoi/config.py
howdoi/shell_utils.py
howdoi/providers/__init__.py
howdoi/providers/anthropic.py
howdoi/providers/base.py
howdoi/providers/openai.py
howdoi_cli-0.1.0.dist-info/LICENSE
howdoi_cli-0.1.0.dist-info/METADATA
howdoi_cli-0.1.0.dist-info/WHEEL
howdoi_cli-0.1.0.dist-info/entry_points.txt
howdoi_cli-0.1.0.dist-info/top_level.txt
howdoi_cli-0.1.0.dist-info/RECORD
