Metadata-Version: 2.2
Name: howdoi-cli
Version: 0.1.0
Summary: AI-powered CLI tool for shell commands
Home-page: https://github.com/mostlydev/howdoi-cli
Author: Wojtek Grabski
Author-email: mostlydev@mostlydev.com
Classifier: Programming Language :: Python :: 3
Classifier: License :: OSI Approved :: MIT License
Classifier: Operating System :: OS Independent
Requires-Python: >=3.6
License-File: LICENSE
Requires-Dist: click
Requires-Dist: pyyaml
Requires-Dist: python-dotenv
Requires-Dist: anthropic
Requires-Dist: openai
Dynamic: author
Dynamic: author-email
Dynamic: classifier
Dynamic: description
Dynamic: description-content-type
Dynamic: home-page
Dynamic: requires-dist
Dynamic: requires-python
Dynamic: summary
